nonebot_adapter_tailchat/__init__.py
nonebot_adapter_tailchat/adapter.py
nonebot_adapter_tailchat/api.py
nonebot_adapter_tailchat/bbcode.py
nonebot_adapter_tailchat/bot.py
nonebot_adapter_tailchat/config.py
nonebot_adapter_tailchat/const.py
nonebot_adapter_tailchat/event.py
nonebot_adapter_tailchat/exception.py
nonebot_adapter_tailchat/message.py
nonebot_adapter_tailchat/model.py
nonebot_adapter_tailchat/permission.py
nonebot_adapter_tailchat/rule.py
nonebot_adapter_tailchat/util.py
nonebot_adapter_tailchat-0.1.0b13.dist-info/LICENSE
nonebot_adapter_tailchat-0.1.0b13.dist-info/METADATA
nonebot_adapter_tailchat-0.1.0b13.dist-info/WHEEL
nonebot_adapter_tailchat-0.1.0b13.dist-info/RECORD
