Metadata-Version: 2.1
Name: nonebot-adapter-tailchat
Version: 0.1.0b13
Summary: NoneBot2 Tailchat 适配器 / Tailchat adapter for nonebot2
Home-page: https://github.com/eya46/nonebot-adapter-tailchat
License: Apache-2.0
Keywords: bot,tailchat,nonebot2
Author: eya46
Author-email: 61458340+eya46@users.noreply.github.com
Requires-Python: >=3.9,<4.0
Classifier: License :: OSI Approved :: Apache Software License
Classifier: Programming Language :: Python :: 3
Classifier: Programming Language :: Python :: 3.9
Classifier: Programming Language :: Python :: 3.10
Classifier: Programming Language :: Python :: 3.11
Classifier: Programming Language :: Python :: 3.12
Classifier: Programming Language :: Python :: 3.13
Requires-Dist: msgpack (>=1.0.8,<2.0.0)
Requires-Dist: nonebot2 (>=2.3.0)
Requires-Dist: pydantic (>=2.0.0)
Requires-Dist: python-socketio[asyncio-client] (>=5.11.2,<6.0.0)
Project-URL: Repository, https://github.com/eya46/nonebot-adapter-tailchat
Project-URL: Tailchat, https://tailchat.msgbyte.com/
